s3dlib/__init__.py
s3dlib/cmap_utilities.py
s3dlib/cmap_xtra.py
s3dlib/surface.py
s3dlib-1.3.0.dist-info/METADATA
s3dlib-1.3.0.dist-info/WHEEL
s3dlib-1.3.0.dist-info/licenses/LICENSE
s3dlib-1.3.0.dist-info/RECORD
